trisul_ai_cli/__init__.py
trisul_ai_cli/cli.py
trisul_ai_cli/client.py
trisul_ai_cli/llm_factory.py
trisul_ai_cli/server.py
trisul_ai_cli/trisul_ai_memory.json
trisul_ai_cli/trp_pb2.py
trisul_ai_cli/assets/logo_tlhs.png
trisul_ai_cli/chroma_store/chroma.sqlite3
trisul_ai_cli/chroma_store/5312074c-3fc1-430c-a1de-75efdbed487d/data_level0.bin
trisul_ai_cli/chroma_store/5312074c-3fc1-430c-a1de-75efdbed487d/header.bin
trisul_ai_cli/chroma_store/5312074c-3fc1-430c-a1de-75efdbed487d/length.bin
trisul_ai_cli/chroma_store/5312074c-3fc1-430c-a1de-75efdbed487d/link_lists.bin
trisul_ai_cli/prompts/system_main.txt
trisul_ai_cli/prompts/system_memory_update.txt
trisul_ai_cli/tools/__init__.py
trisul_ai_cli/tools/json_to_toon_converter.py
trisul_ai_cli/tools/pdf_to_chroma_ingest.py
trisul_ai_cli/tools/utils.py
trisul_ai_cli-0.2.5.dist-info/METADATA
trisul_ai_cli-0.2.5.dist-info/WHEEL
trisul_ai_cli-0.2.5.dist-info/entry_points.txt
trisul_ai_cli-0.2.5.dist-info/top_level.txt
trisul_ai_cli-0.2.5.dist-info/RECORD
