Metadata-Version: 2.4
Name: trisul_ai_cli
Version: 0.2.5
Summary: Trisul AI CLI that starts a local MCP server and a client.
Author: Parthasarathy B
Author-email: partha@unleashnetworks.com
License: MIT
Classifier: Programming Language :: Python :: 3
Classifier: License :: OSI Approved :: MIT License
Classifier: Operating System :: OS Independent
Requires-Python: >=3.8
Requires-Dist: nest_asyncio
Requires-Dist: mcp
Requires-Dist: chromadb
Requires-Dist: pyzmq
Requires-Dist: protobuf
Requires-Dist: matplotlib
Requires-Dist: python-dotenv
Requires-Dist: reportlab
Requires-Dist: stdiomask
Requires-Dist: langchain
Requires-Dist: langchain-google-genai
Requires-Dist: langchain-openai
Requires-Dist: langchain-anthropic
Requires-Dist: langchain-community
Requires-Dist: voyageai
